{
  "name": "Delia Pearson",
  "age": 63,
  "address": {
    "street": "Bucmun Court",
    "city": "Sinemca",
    "state": "SD",
    "zip": "08151"
  },
  "contact": {
    "phone": "(376) 789-4968",
    "servicePhone": "800574684"
  },
  "birthday": "1980-01-30T15:16:32.478Z",
  "ip": "163.97.246.60",
  "foo": "bar",
  "profile": {
    "about": "Alizecis igecim ezo dasedana ca ewdozfi zutu uvisi junlubaw jedzet zo gug wouhazi ciom zinkuf ado mi pe. Duc vic neeh wofomhan vu tesoflu seimi aduga ive miner ho semki. Ce wukuhew esa ru oducit kim selef jeb amukirnis rod so alo coufdaz basiwu cit. Raneef dar zakhagil azacagbut madipuzu nofumpis iveegu ma moog hom pa diwif weveja sunad.",
    "bio": "Sahno kiew fi bipus luk sacozju esi diliruz ijo amjuul maro po hidedpin cucabne ruv luso. Kuwuhrur pajde ferzawe sorohaz zobil jevah no sora fa hevkemug evsu hoz sut ke. Boucehu noggikpor gotedi jerah wacokica nit alra baztoum hohep jub mo vojil bufpi sol furi romeh wu jimuwkuz. Imuflaw gugup wi waub cas efeja janu cigvivbu uka jeveljaf do vukiko wafhapofi. Afjo aguv lewho gu kirera rongoada mekace sigajoz gaj vesibi mi ho ra nicjano me. Uhwic ner ituziok isro gesim dubepe rat vidiwuh odhepeb gekev bad wuku kaanze rij gej puverwod iwcifod cimiopu."
  },
  "apiKey": "0c0da1f061b5c5bd8b8d33c0d55e1f86fcd46cb6cb984ad70056de3cbff971a1",
  "currency": {
    "code": "SCR",
    "name": "Seychelles Rupee"
  }
}