{
  "name": "Lula Hanson",
  "age": 31,
  "address": {
    "street": "Hatto Turnpike",
    "city": "Waafufu",
    "state": "SD",
    "zip": "67199"
  },
  "contact": {
    "phone": "(549) 737-2975",
    "servicePhone": "800823937"
  },
  "birthday": "1960-12-30T22:28:18.891Z",
  "ip": "86.185.1.160",
  "foo": "bar",
  "profile": {
    "about": "Fe ginhecwal ezharjan fekjah cepikuk lujsesid ce tioji ler vever apka nen fekce norciwviz. Fuz fof vajube huno vapmep lemab fifobi ginpug saguk vora or af garto. Jegolic kovza ja izeove ibair oz othuv bozvovik dewoc kepjiwe suniwze ogofunhe piwage ov.",
    "bio": "Tawiw sougpo lohepok ke ikuhuwu usujiva mim kebisow womsockif vides ima mu sa rozuvuijo hejmofcem. Cop luzogi udikulu pok siftuc bugul no jipa zucratu pat leemtaw uhugo jas pece ti dehadnap tumu zuh. Veso has cum ma do davbuk telu var gozodeh uvehov hul kuji kocmu."
  },
  "apiKey": "a836c92a6904518b948e516c9d480a3d80e480f31c7da6419a2c5fdda466d78b",
  "currency": {
    "code": "VEF",
    "name": "Venezuela Bolivar"
  }
}