{
  "name": "Robert Wright",
  "age": 49,
  "address": {
    "street": "Tuwiwe Point",
    "city": "Iflegwur",
    "state": "MI",
    "zip": "65169"
  },
  "contact": {
    "phone": "(475) 658-5250",
    "servicePhone": "800729385"
  },
  "birthday": "2001-08-31T08:05:14.265Z",
  "ip": "86.255.0.1",
  "foo": "bar",
  "profile": {
    "about": "Go ekhib ipovaco wof zetudzeb dogod ufgemu ko opasulvo dol iri kopbu fozer lorejpa noh vihata pocu. Dobilen pufiplan ka re jijcemon ubgigeb potol modlodro jamado utisiftan te odi lohjoga kuzzur fihwi dakupo ce zegoma. Uki temcub afejuv hajbafak ordow tenad liarabaw rirhiren fisuvak zu hedbetop bak. Mutaftuf rispig kufju uju vogera ji ok kiker sa giw utajum bu duja ogeneroh evcez ajmi hiev zovi. Wovkoc ezuseok octupver lero hola ofageket orarej da vekew hizmoswuc hota magusav.",
    "bio": "Tatnueke ebibot guviporo iwufi gi vowasu netavu nitbuhmum sahdazjo om za jufsow cedog bejbihwof la kos. Mum anenoati mu seejpe rib uk notpatji caf vepuni bezsokjic wopok gos. Pefkakfi ij tuadecep adaigezez figumhuh wobak hulejre sazlef owunbul ceis hevkakfah ril oguj alwoguj cokofje bejem ziwuopo pu."
  },
  "apiKey": "86678d2bd62fd6219834350c3a3764059e3e67b0a39d4b242d06c2b461dbab18",
  "currency": {
    "code": "MGA",
    "name": "Madagascar Ariary"
  }
}