{
  "name": "Carlos Robinson",
  "age": 30,
  "address": {
    "street": "Puuho View",
    "city": "Ihmovip",
    "state": "TX",
    "zip": "41473"
  },
  "contact": {
    "phone": "(640) 903-2514",
    "servicePhone": "800451544"
  },
  "birthday": "1997-09-23T21:27:35.109Z",
  "ip": "77.187.108.47",
  "foo": "bar",
  "profile": {
    "about": "Kokavo rol pipgo vob sikibne tazebi koku had lagocmel tol we basazi nu zo lev. Liogelec muj bewkuih kurab pohhirih maowmem zid nowfigfu fahfuc bihna jo ereh udnurhez jo. Venojmu il nume hev eheuho fupsoz zebroni legagoril ba atnuljof mat ope cowlol vo reh mehu emhuzwi rufiw. Tijutuv tavpiohu bedzakco imzo do imin bu becju gelop piifi ope as fuvu huogu zitibiwe toozeno ag. Godehop jeces med andi uwadowo rajcog punesu ufbida lerutuc zusozi uwe ov api taomho nu iviniew odto pucetafu.",
    "bio": "Kisiv ri lelsohha im cihpe mibob fok zejco mohusata de zimomi hassom zofe dukuf om ne. Ligsu mowupzip zum naatmop nudnozmod ufur eho opciwmeb saso se makri ulekes imva zi. Rab ro bah bojan fi eb ofwabo wece guwmirwah coztojo kuaka lo icwijtov lifhozho neigmaf er rame. Hamok vuwgoltaw we devunenu ru tuva buk seevvoh renfa ujegajew co uhtaz nivnumcu wobibuv. On hor emubu ge wiz zofse tu tuokcis eguleki bomewvem nauze hanhufin izbetov ze takave gi. Ko ubovbab luw giplimir bet fuwjohfa zad di ibofugped so rim vus ek ib. Basugekip od so opu lulacko mucka wirgiedu fo sirosjaz rosve li nuswiwa difzudum jubruhsos nefku gohkez ti re."
  },
  "apiKey": "b6d08fa30e7625d59abb7f930b41b94bbbf37536371dcc27ab004b9ba4040367",
  "currency": {
    "code": "IQD",
    "name": "Iraq Dinar"
  }
}